{"Exif":{"Lat":40.49179,"Long":-6.05324,"Date":"2022-08-05T12:58:00+02:00","Tags":{"ApertureValue":6,"Artist":"Rom Gostomski","Copyright":"Rom Gostomski","CustomRendered|int":"1","DateTimeDigitized|time.Time":"2022-08-16T08:56:00+02:00","DateTimeOriginal|time.Time":"2022-08-05T12:58:00+02:00","DateTime|time.Time":"2022-08-05T12:58:00+02:00","ExposureTime|*big.Rat":"1/125","FNumber":8,"FileSource":"","FocalLength":55,"GainControl|int":"0","ISOSpeedRatings|int":"125","LensMake":"Mamiya","LensModel":"Mamiya Sekor C 1:2.8 55mm","LightSource|int":"1","Make":"Mamiya","Model":"M645 1000S","PixelXDimension|int":"1920","PixelYDimension|int":"1920","SceneCaptureType|int":"0","SceneType":"","ShutterSpeedValue":6.965784,"Software":"Capture One 23 Macintosh","SubSecTimeOriginal":"65","SubjectDistanceRange|int":"0","SubjectDistance|*big.Rat":"3/8"}}}
